samar/__init__.py
samar/analyse.py
samar/compute.py
samar/config.yaml
samar/draw.py
samar/util.py
samar-0.0.3.dist-info/LICENSE
samar-0.0.3.dist-info/METADATA
samar-0.0.3.dist-info/WHEEL
samar-0.0.3.dist-info/RECORD
